app/__init__.py
app/app_config.py
app/app_run.py
app/app_test.py
app/test.py
base/__init__.py
base/app/__init__.py
base/app/base_app.py
base/config/__init__.py
base/config/base_config.py
base/data/__init__.py
base/data/base_data_loader.py
base/data/base_data_process.py
base/data/base_data_reader.py
base/evaluation/__init__.py
base/evaluation/base_evaluator.py
base/loss/__init__.py
base/loss/base_loss.py
base/model/__init__.py
base/model/base_model.py
base/runner/__init__.py
base/runner/base_runner.py
classification/__init__.py
classification/app/__init__.py
classification/app/f_zp_gp_app.py
classification/config/__init__.py
classification/config/fast_text_config.py
classification/data/__init__.py
classification/data/data_process.py
classification/data/data_stats.py
classification/evaluation/__init__.py
classification/evaluation/classify_evaluator.py
classification/model/__init__.py
classification/model/text_cnn.py
classification/runner/__init__.py
classification/runner/runner_fast_text.py
classification/utils/__init__.py
classification/utils/utils.py
doc_event/__init__.py
doc_event/app/__init__.py
doc_event/app/the_belt_and_road_app.py
doc_event/config/__init__.py
doc_event/data/__init__.py
doc_event/data/data_loader.py
doc_event/data/data_process.py
doc_event/data/data_split.py
doc_event/evaluate/__init__.py
doc_event/evaluate/eval_entity.py
doc_event/model/__init__.py
doc_event/model/crf.py
doc_event/model/seqlabel.py
doc_event/model/wordrep.py
doc_event/model/wordsequence.py
doc_event/runner/__init__.py
doc_event/runner/runner.py
doc_event/utils/__init__.py
doc_event/utils/alphabet.py
doc_event/utils/functions.py
doc_similarity/__init__.py
doc_similarity/app/__init__.py
doc_similarity/app/doc_sim_app.py
doc_similarity/data/__init__.py
doc_similarity/data/compare.py
doc_similarity/data/data_loader.py
doc_similarity/data/data_process.py
doc_similarity/model/__init__.py
doc_similarity/model/base_similarity.py
doc_similarity/model/cosine_similarity.py
zzsn_nlp-0.0.1.dist-info/LICENSE
zzsn_nlp-0.0.1.dist-info/METADATA
zzsn_nlp-0.0.1.dist-info/WHEEL
zzsn_nlp-0.0.1.dist-info/top_level.txt
zzsn_nlp-0.0.1.dist-info/RECORD
