Metadata-Version: 2.1
Name: zzsn-nlp
Version: 0.0.1
Summary: zzsn
Home-page: https://gitee.com/ly_love_ly/zzsn_nlp
Author: ygg
Author-email: ygg@zut.edu.cn
License: UNKNOWN
Platform: UNKNOWN
Classifier: Programming Language :: Python :: 3
Classifier: License :: OSI Approved :: MIT License
Classifier: Operating System :: OS Independent
